{"path":"/device/identifier/Macmini5,1.html","noAds":true,"frontmatter":{"title":"Mac mini (Mid 2011, Integrated graphics)","hideTitle":true,"description":"Information lookup for Mac mini (Mid 2011, Integrated graphics)","chartType":"device","widePage":false,"device":[{"name":"Mac mini (Mid 2011, Integrated graphics)","identifier":["Macmini5,1"],"key":"Macmini5,1","released":"2011-07-20","arch":"x86-64","model":["A1347"],"board":[],"type":"Mac mini"}],"versionArr":[],"hasFirmwares":{"release":false,"beta":false,"internal":false},"hasFirmwareFilters":false,"grouped":false,"imgCount":0,"noJb":true,"jbCount":0,"img":{"count":1,"dark":false,"key":"Macmini5,1"},"deviceFilter":[{"label":"Mac mini (Mid 2011, Integrated graphics)","value":"Macmini5,1"}],"head":[["meta",{"property":"og:image","content":"https://img.appledb.dev/device@256/Macmini5,1/0.png"}]],"sidebar":false,"editLink":false,"lastUpdated":false,"contributors":false}}